Workbook
Name NativeTimeline_Date: #N/A
Name Slicer_Category: #N/A
Name Slicer_Months__Date: #N/A
Name Slicer_Region: #N/A

Sheet DASHBOARD
H21: =PIVOT_TABLES!B9 -> 229442.5

Sheet PIVOT_TABLES
A2: REGIONAL SALES | U2: =GETPIVOTDATA("Sum of Total_Amount",$A$3) -> 229442.5
A3: Row Labels | B3: Sum of Total_Amount
A4: Central | B4: 41538.37
A5: East | B5: 59288.39
A6: North | B6: 50808.31
A7: South | B7: 36398.75
A8: West | B8: 41408.68
A9: Grand Total | B9: 229442.5
A11: PRODUCT SALES
A12: Row Labels | B12: Sum of Total_Amount
A13: Blender | B13: 5219.13
A14: Bookshelf | B14: 15298.98
A15: Coffee Maker | B15: 3119.61
A16: Desk | B16: 23399.22
A17: Headphones | B17: 7049.53
A18: Keyboard | B18: 8009.11
A19: Laptop | B19: 67499.25
A20: Monitor | B20: 22249.15
A21: Office Chair | B21: 10399.48
A22: Smartphone | B22: 67199.04
A23: Grand Total | B23: 229442.5
A25: MONTHLY SALES
A26: Row Labels | B26: Sum of Total_Amount
A27: Jan | B27: 25799.15
A28: Feb | B28: 16069.38
A29: Mar | B29: 19899.38
A30: Apr | B30: 28149.19
A31: May | B31: 17039.35
A32: Jun | B32: 19299.45
A33: Jul | B33: 18479.4
A34: Aug | B34: 15759.43
A35: Sep | B35: 12989.51
A36: Oct | B36: 20609.52
A37: Nov | B37: 12309.44
A38: Dec | B38: 23039.3
A39: Grand Total | B39: 229442.5

Sheet STATE REGION MAP
A1: State | B1: Region | D1: SELECT REGION | E1: MAP VALUE
A2: Jammu and Kashmir | B2: North | D2: North | E2: =IF(B2=$D$2,1,"") -> 1
A3: Ladakh | B3: North | E3: =IF(B3=$D$2,1,"") -> 1
A4: Himachal Pradesh | B4: North | E4: =IF(B4=$D$2,1,"") -> 1
A5: Punjab | B5: North | E5: =IF(B5=$D$2,1,"") -> 1
A6: Chandigarh | B6: North | E6: =IF(B6=$D$2,1,"") -> 1
A7: Uttarakhand | B7: North | E7: =IF(B7=$D$2,1,"") -> 1
A8: Haryana | B8: North | E8: =IF(B8=$D$2,1,"") -> 1
A9: Delhi | B9: North | E9: =IF(B9=$D$2,1,"") -> 1
A10: Rajasthan | B10: North | E10: =IF(B10=$D$2,1,"") -> 1
A11: Uttar Pradesh | B11: North | E11: =IF(B11=$D$2,1,"") -> 1
A12: Madhya Pradesh | B12: Central | E12: =IF(B12=$D$2,1,"")
A13: Chhattisgarh | B13: Central | E13: =IF(B13=$D$2,1,"")
A14: Maharashtra | B14: West | E14: =IF(B14=$D$2,1,"")
... A36: Nagaland | B36: East | E36: =IF(B36=$D$2,1,"")
A37: Tripura | B37: East

Sheet Data Intelligence Dashboard
A1: Transaction_ID | B1: Date | C1: Customer_ID | D1: Customer_Name | E1: Product_ID | F1: Product_Name | G1: Category | H1: Quantity | I1: Unit_Price | J1: Payment_Method | K1: Region | L1: Customer_Segment | M1: Customer_Since | N1: Total_Amount | O1: Customer_Tenure | P1: Current_Date | Q1: Timestamp | R1: Month_End
A2: TRX0155 | B2: 45393 | C2: CUST023 | D2: Paul Baker | E2: P009 | F2: Monitor | G2: Electronics | H2: 3 | I2: 333.33333 | J2: Cash | K2: Central | L2: Basic | M2: 44425 | N2: =H2*I2 -> 1000 | O2: =DATEDIF(M2,TODAY(),"Y") -> 5 | P2: =TODAY() -> 46305 | Q2: =IF(A2<>"",IF(Q2="",NOW(),Q2),"") -> 0 | R2: =EOMONTH(M2,0) -> 44439
A3: TRX0023 | B3: 45396 | C3: CUST013 | D3: Joseph Jackson | E3: P009 | F3: Monitor | G3: Electronics | H3: 3 | I3: 249.99 | J3: Credit Card | K3: Central | L3: Premium | M3: 44575 | N3: =H3*I3 -> 749.97 | O3: =DATEDIF(M3,TODAY(),"Y") -> 4 | P3: =TODAY() -> 46305 | Q3: =IF(A3<>"",IF(Q3="",NOW(),Q3),"") -> 0 | R3: =EOMONTH(M3,0) -> 44592
A4: TRX0139 | B4: 45399 | C4: CUST021 | D4: Kevin Scott | E4: P005 | F4: Blender | G4: Appliances | H4: 3 | I4: 59.99 | J4: PayPal | K4: South | L4: Standard | M4: 45262 | N4: =H4*I4 -> 179.97 | O4: =DATEDIF(M4,TODAY(),"Y") -> 2 | P4: =TODAY() -> 46305 | Q4: =IF(A4<>"",IF(Q4="",NOW(),Q4),"") -> 0 | R4: =EOMONTH(M4,0) -> 45291
A5: TRX0043 | B5: 45400 | C5: CUST046 | D5: Kathleen Bennett | E5: P005 | F5: Blender | G5: Appliances | H5: 3 | I5: 59.99 | J5: Cash | K5: North | L5: Premium | M5: 45114 | N5: =H5*I5 -> 179.97 | O5: =DATEDIF(M5,TODAY(),"Y") -> 3 | P5: =TODAY() -> 46305 | Q5: =IF(A5<>"",IF(Q5="",NOW(),Q5),"") -> 0 | R5: =EOMONTH(M5,0) -> 45138
A6: TRX0212 | B6: 45400 | C6: CUST003 | D6: Michael Brown | E6: P008 | F6: Bookshelf | G6: Furniture | H6: 5 | I6: 149.99 | J6: Credit Card | K6: North | L6: Premium | M6: 45295 | N6: =H6*I6 -> 749.95 | O6: =DATEDIF(M6,TODAY(),"Y") -> 2 | P6: =TODAY() -> 46305 | Q6: =IF(A6<>"",IF(Q6="",NOW(),Q6),"") -> 0 | R6: =EOMONTH(M6,0) -> 45322
A7: TRX0092 | B7: 45403 | C7: CUST024 | D7: Dorothy Nelson | E7: P005 | F7: Blender | G7: Appliances | H7: 2 | I7: 59.99 | J7: Cash | K7: West | L7: Standard | M7: 44746 | N7: =H7*I7 -> 119.98 | O7: =DATEDIF(M7,TODAY(),"Y") -> 4 | P7: =TODAY() -> 46305 | Q7: =IF(A7<>"",IF(Q7="",NOW(),Q7),"") -> 0 | R7: =EOMONTH(M7,0) -> 44773
A8: TRX0193 | B8: 45403 | C8: CUST024 | D8: Dorothy Nelson | E8: P003 | F8: Headphones | G8: Electronics | H8: 5 | I8: 149.99 | J8: Credit Card | K8: Central | L8: Standard | M8: 44418 | N8: =H8*I8 -> 749.95 | O8: =DATEDIF(M8,TODAY(),"Y") -> 5 | P8: =TODAY() -> 46305 | Q8: =IF(A8<>"",IF(Q8="",NOW(),Q8),"") -> 0 | R8: =EOMONTH(M8,0) -> 44439
A9: TRX0240 | B9: 45403 | C9: CUST017 | D9: Charles Allen | E9: P005 | F9: Blender | G9: Appliances | H9: 3 | I9: 59.99 | J9: Debit Card | K9: South | L9: Basic | M9: 45007 | N9: =H9*I9 -> 179.97 | O9: =DATEDIF(M9,TODAY(),"Y") -> 3 | P9: =TODAY() -> 46305 | Q9: =IF(A9<>"",IF(Q9="",NOW(),Q9),"") -> 0 | R9: =EOMONTH(M9,0) -> 45016
A10: TRX0135 | B10: 45405 | C10: CUST009 | D10: Robert Thomas | E10: P001 | F10: Laptop | G10: Electronics | H10: 3 | I10: 899.99 | J10: PayPal | K10: East | L10: Standard | M10: 45299 | N10: =H10*I10 -> 2699.97 | O10: =DATEDIF(M10,TODAY(),"Y") -> 2 | P10: =TODAY() -> 46305 | Q10: =IF(A10<>"",IF(Q10="",NOW(),Q10),"") -> 0 | R10: =EOMONTH(M10,0) -> 45322
A11: TRX0185 | B11: 45408 | C11: CUST026 | D11: Karen Hill | E11: P005 | F11: Blender | G11: Appliances | H11: 3 | I11: 59.99 | J11: Cash | K11: West | L11: Premium | M11: 45207 | N11: =H11*I11 -> 179.97 | O11: =DATEDIF(M11,TODAY(),"Y") -> 3 | P11: =TODAY() -> 46305 | Q11: =IF(A11<>"",IF(Q11="",NOW(),Q11),"") -> 0 | R11: =EOMONTH(M11,0) -> 45230
A12: TRX0138 | B12: 45408 | C12: CUST022 | D12: Susan Green | E12: P008 | F12: Bookshelf | G12: Furniture | H12: 1 | I12: 149.99 | J12: Credit Card | K12: West | L12: Standard | M12: 45103 | N12: =H12*I12 -> 149.99 | O12: =DATEDIF(M12,TODAY(),"Y") -> 3 | P12: =TODAY() -> 46305 | Q12: =IF(A12<>"",IF(Q12="",NOW(),Q12),"") -> 0 | R12: =EOMONTH(M12,0) -> 45107
A13: TRX0209 | B13: 45408 | C13: CUST046 | D13: Kathleen Bennett | E13: P008 | F13: Bookshelf | G13: Furniture | H13: 5 | I13: 149.99 | J13: Debit Card | K13: North | L13: Basic | M13: 44830 | N13: =H13*I13 -> 749.95 | O13: =DATEDIF(M13,TODAY(),"Y") -> 4 | P13: =TODAY() -> 46305 | Q13: =IF(A13<>"",IF(Q13="",NOW(),Q13),"") -> 0 | R13: =EOMONTH(M13,0) -> 44834
... A251: TRX0064 | B251: 45758 | C251: CUST031 | D251: Steven Turner | E251: P010 | F251: Keyboard | G251: Electronics | H251: 3 | I251: 89.99 | J251: Debit Card | K251: North | L251: Premium | M251: 44878 | N251: =H251*I251 -> 269.97 | O251: =DATEDIF(M251,TODAY(),"Y") -> 3 | P251: =TODAY() -> 46305 | Q251: =IF(A251<>"",IF(Q251="",NOW(),Q251),"") -> 0 | R251: =EOMONTH(M251,0) -> 44895

Sheet TOTAL SALES PER WEEK
A2: TOTAL SALES PER WEEK
A3: Row Labels | B3: Sum of Total_Amount
A4: 4/11/2024 - 4/17/2024 | B4: 1929.94
A5: 4/18/2024 - 4/24/2024 | B5: 4679.79
A6: 4/25/2024 - 5/1/2024 | B6: 17359.59
A7: 5/2/2024 - 5/8/2024 | B7: 2199.92
A8: 5/9/2024 - 5/15/2024 | B8: 4799.71
A9: 5/16/2024 - 5/22/2024 | B9: 2549.91
A10: 5/23/2024 - 5/29/2024 | B10: 4609.86
A11: 5/30/2024 - 6/5/2024 | B11: 739.91
A12: 6/6/2024 - 6/12/2024 | B12: 1879.88
A13: 6/13/2024 - 6/19/2024 | B13: 10289.8
A14: 6/20/2024 - 6/26/2024 | B14: 619.93
A15: 6/27/2024 - 7/3/2024 | B15: 6609.83
... A57: Grand Total | B57: 229442.5

Sheet WEEKLY DATA
A1: Transaction_ID | B1: Date | C1: Customer_ID | D1: Customer_Name | E1: Product_ID | F1: Product_Name | G1: Category | H1: Quantity | I1: Unit_Price | J1: Payment_Method | K1: Region | L1: Customer_Segment | M1: Customer_Since | N1: Total_Amount
A2: TRX0155 | B2: 45393 | C2: CUST023 | D2: Paul Baker | E2: P009 | F2: Monitor | G2: Electronics | H2: 3 | I2: 333.33333 | J2: Cash | K2: Central | L2: Basic | M2: 44425 | N2: =H2*I2 -> 1000
A3: TRX0023 | B3: 45396 | C3: CUST013 | D3: Joseph Jackson | E3: P009 | F3: Monitor | G3: Electronics | H3: 3 | I3: 249.99 | J3: Credit Card | K3: Central | L3: Premium | M3: 44575 | N3: =H3*I3 -> 749.97
A4: TRX0139 | B4: 45399 | C4: CUST021 | D4: Kevin Scott | E4: P005 | F4: Blender | G4: Appliances | H4: 3 | I4: 59.99 | J4: PayPal | K4: South | L4: Standard | M4: 45262 | N4: =H4*I4 -> 179.97
A5: TRX0043 | B5: 45400 | C5: CUST046 | D5: Kathleen Bennett | E5: P005 | F5: Blender | G5: Appliances | H5: 3 | I5: 59.99 | J5: Cash | K5: North | L5: Premium | M5: 45114 | N5: =H5*I5 -> 179.97
A6: TRX0212 | B6: 45400 | C6: CUST003 | D6: Michael Brown | E6: P008 | F6: Bookshelf | G6: Furniture | H6: 5 | I6: 149.99 | J6: Credit Card | K6: North | L6: Premium | M6: 45295 | N6: =H6*I6 -> 749.95
A7: TRX0092 | B7: 45403 | C7: CUST024 | D7: Dorothy Nelson | E7: P005 | F7: Blender | G7: Appliances | H7: 2 | I7: 59.99 | J7: Cash | K7: West | L7: Standard | M7: 44746 | N7: =H7*I7 -> 119.98
A8: TRX0193 | B8: 45403 | C8: CUST024 | D8: Dorothy Nelson | E8: P003 | F8: Headphones | G8: Electronics | H8: 5 | I8: 149.99 | J8: Credit Card | K8: Central | L8: Standard | M8: 44418 | N8: =H8*I8 -> 749.95
A9: TRX0240 | B9: 45403 | C9: CUST017 | D9: Charles Allen | E9: P005 | F9: Blender | G9: Appliances | H9: 3 | I9: 59.99 | J9: Debit Card | K9: South | L9: Basic | M9: 45007 | N9: =H9*I9 -> 179.97
A10: TRX0135 | B10: 45405 | C10: CUST009 | D10: Robert Thomas | E10: P001 | F10: Laptop | G10: Electronics | H10: 3 | I10: 899.99 | J10: PayPal | K10: East | L10: Standard | M10: 45299 | N10: =H10*I10 -> 2699.97
A11: TRX0185 | B11: 45408 | C11: CUST026 | D11: Karen Hill | E11: P005 | F11: Blender | G11: Appliances | H11: 3 | I11: 59.99 | J11: Cash | K11: West | L11: Premium | M11: 45207 | N11: =H11*I11 -> 179.97
A12: TRX0138 | B12: 45408 | C12: CUST022 | D12: Susan Green | E12: P008 | F12: Bookshelf | G12: Furniture | H12: 1 | I12: 149.99 | J12: Credit Card | K12: West | L12: Standard | M12: 45103 | N12: =H12*I12 -> 149.99
A13: TRX0209 | B13: 45408 | C13: CUST046 | D13: Kathleen Bennett | E13: P008 | F13: Bookshelf | G13: Furniture | H13: 5 | I13: 149.99 | J13: Debit Card | K13: North | L13: Basic | M13: 44830 | N13: =H13*I13 -> 749.95
... A251: TRX0064 | B251: 45758 | C251: CUST031 | D251: Steven Turner | E251: P010 | F251: Keyboard | G251: Electronics | H251: 3 | I251: 89.99 | J251: Debit Card | K251: North | L251: Premium | M251: 44878 | N251: =H251*I251 -> 269.97

Sheet FILTER ANALYSIS_N&S
A1: NORTH REGION FILTER | P1: SOUTH REGION FILTER
A2: Transaction_ID | B2: Date | C2: Customer_ID | D2: Customer_Name | E2: Product_ID | F2: Product_Name | G2: Category | H2: Quantity | I2: Unit_Price | J2: Payment_Method | K2: Region | L2: Customer_Segment | M2: Customer_Since | N2: Total_Amount | P2: Transaction_ID | Q2: Date | R2: Customer_ID | S2: Customer_Name | T2: Product_ID | U2: Product_Name | V2: Category | W2: Quantity | X2: Unit_Price | Y2: Payment_Method | Z2: Region | AA2: Customer_Segment | AB2: Customer_Since | AC2: Total_Amount
A3: {=_xlfn._xlws.FILTER('Data Intelligence Dashboard'!A2:N251,'Data Intelligence Dashboard'!K2:K251="North")} -> TRX0043 | B3: 45400 | C3: CUST046 | D3: Kathleen Bennett | E3: P005 | F3: Blender | G3: Appliances | H3: 3 | I3: 59.99 | J3: Cash | K3: North | L3: Premium | M3: 45114 | N3: 179.97 | P3: {=_xlfn._xlws.FILTER('Data Intelligence Dashboard'!A2:N251,'Data Intelligence Dashboard'!K2:K251="SOUTH")} -> TRX0139 | Q3: 45399 | R3: CUST021 | S3: Kevin Scott | T3: P005 | U3: Blender | V3: Appliances | W3: 3 | X3: 59.99 | Y3: PayPal | Z3: South | AA3: Standard | AB3: 45262 | AC3: 179.97
A4: TRX0212 | B4: 45400 | C4: CUST003 | D4: Michael Brown | E4: P008 | F4: Bookshelf | G4: Furniture | H4: 5 | I4: 149.99 | J4: Credit Card | K4: North | L4: Premium | M4: 45295 | N4: 749.95 | P4: TRX0240 | Q4: 45403 | R4: CUST017 | S4: Charles Allen | T4: P005 | U4: Blender | V4: Appliances | W4: 3 | X4: 59.99 | Y4: Debit Card | Z4: South | AA4: Basic | AB4: 45007 | AC4: 179.97
A5: TRX0209 | B5: 45408 | C5: CUST046 | D5: Kathleen Bennett | E5: P008 | F5: Bookshelf | G5: Furniture | H5: 5 | I5: 149.99 | J5: Debit Card | K5: North | L5: Basic | M5: 44830 | N5: 749.95 | P5: TRX0029 | Q5: 45427 | R5: CUST017 | S5: Charles Allen | T5: P006 | U5: Office Chair | V5: Furniture | W5: 5 | X5: 199.99 | Y5: Cash | Z5: South | AA5: Standard | AB5: 44412 | AC5: 999.95
A6: TRX0246 | B6: 45408 | C6: CUST041 | D6: Peter Richardson | E6: P008 | F6: Bookshelf | G6: Furniture | H6: 3 | I6: 149.99 | J6: Cash | K6: North | L6: Premium | M6: 44806 | N6: 449.97 | P6: TRX0021 | Q6: 45435 | R6: CUST006 | S6: Lisa Anderson | T6: P004 | U6: Coffee Maker | V6: Appliances | W6: 3 | X6: 79.99 | Y6: Cash | Z6: South | AA6: Basic | AB6: 45046 | AC6: 239.97
A7: TRX0067 | B7: 45409 | C7: CUST043 | D7: Dennis Gray | E7: P005 | F7: Blender | G7: Appliances | H7: 3 | I7: 59.99 | J7: Credit Card | K7: North | L7: Standard | M7: 45351 | N7: 179.97 | P7: TRX0121 | Q7: 45449 | R7: CUST028 | S7: Betty Campbell | T7: P010 | U7: Keyboard | V7: Electronics | W7: 1 | X7: 89.99 | Y7: Credit Card | Z7: South | AA7: Standard | AB7: 44582 | AC7: 89.99
A8: TRX0230 | B8: 45409 | C8: CUST027 | D8: George Adams | E8: P001 | F8: Laptop | G8: Electronics | H8: 1 | I8: 899.99 | J8: Debit Card | K8: North | L8: Standard | M8: 44920 | N8: 899.99 | P8: TRX0115 | Q8: 45459 | R8: CUST012 | S8: Patricia Moore | T8: P010 | U8: Keyboard | V8: Electronics | W8: 2 | X8: 89.99 | Y8: Credit Card | Z8: South | AA8: Premium | AB8: 44471 | AC8: 179.98
A9: TRX0049 | B9: 45410 | C9: CUST025 | D9: Mark Carter | E9: P008 | F9: Bookshelf | G9: Furniture | H9: 4 | I9: 149.99 | J9: Debit Card | K9: North | L9: Premium | M9: 45374 | N9: 599.96 | P9: TRX0154 | Q9: 45459 | R9: CUST023 | S9: Paul Baker | T9: P001 | U9: Laptop | V9: Electronics | W9: 5 | X9: 899.99 | Y9: Credit Card | Z9: South | AA9: Standard | AB9: 44974 | AC9: 4499.95
A10: TRX0134 | B10: 45410 | C10: CUST010 | D10: Maria Garcia | E10: P002 | F10: Smartphone | G10: Electronics | H10: 2 | I10: 699.99 | J10: Cash | K10: North | L10: Basic | M10: 44781 | N10: 1399.98 | P10: TRX0025 | Q10: 45468 | R10: CUST049 | S10: Raymond Ross | T10: P010 | U10: Keyboard | V10: Electronics | W10: 4 | X10: 89.99 | Y10: Debit Card | Z10: South | AA10: Basic | AB10: 45281 | AC10: 359.96
A11: TRX0222 | B11: 45410 | C11: CUST048 | D11: Virginia Sanders | E11: P009 | F11: Monitor | G11: Electronics | H11: 3 | I11: 249.99 | J11: Credit Card | K11: North | L11: Premium | M11: 45224 | N11: 749.97 | P11: TRX0052 | Q11: 45476 | R11: CUST022 | S11: Susan Green | T11: P010 | U11: Keyboard | V11: Electronics | W11: 1 | X11: 89.99 | Y11: Cash | Z11: South | AA11: Standard | AB11: 44611 | AC11: 89.99
A12: TRX0204 | B12: 45415 | C12: CUST044 | D12: Cynthia Price | E12: P009 | F12: Monitor | G12: Electronics | H12: 4 | I12: 249.99 | J12: PayPal | K12: North | L12: Standard | M12: 44468 | N12: 999.96 | P12: TRX0136 | Q12: 45482 | R12: CUST049 | S12: Raymond Ross | T12: P005 | U12: Blender | V12: Appliances | W12: 4 | X12: 59.99 | Y12: Cash | Z12: South | AA12: Standard | AB12: 44509 | AC12: 239.96
A13: TRX0004 | B13: 45424 | C13: CUST012 | D13: Patricia Moore | E13: P010 | F13: Keyboard | G13: Electronics | H13: 5 | I13: 89.99 | J13: Cash | K13: North | L13: Premium | M13: 44919 | N13: 449.95 | P13: TRX0244 | Q13: 45497 | R13: CUST013 | S13: Joseph Jackson | T13: P001 | U13: Laptop | V13: Electronics | W13: 5 | X13: 899.99 | Y13: Debit Card | Z13: South | AA13: Standard | AB13: 44899 | AC13: 4499.95
A14: TRX0245 | B14: 45438 | C14: CUST031 | D14: Steven Turner | E14: P006 | F14: Office Chair | G14: Furniture | H14: 3 | I14: 199.99 | J14: Credit Card | K14: North | L14: Premium | M14: 45292 | N14: 599.97 | P14: TRX0228 | Q14: 45500 | R14: CUST019 | S14: Daniel King | T14: P007 | U14: Desk | V14: Furniture | W14: 1 | X14: 299.99 | Y14: Cash | Z14: South | AA14: Basic | AB14: 44982 | AC14: 299.99
A15: TRX0042 | B15: 45443 | C15: CUST019 | D15: Daniel King | E15: P004 | F15: Coffee Maker | G15: Appliances | H15: 1 | I15: 79.99 | J15: Cash | K15: North | L15: Standard | M15: 44917 | N15: 79.99 | P15: TRX0157 | Q15: 45501 | R15: CUST025 | S15: Mark Carter | T15: P010 | U15: Keyboard | V15: Electronics | W15: 2 | X15: 89.99 | Y15: PayPal | Z15: South | AA15: Basic | AB15: 44976 | AC15: 179.98
... A44: TRX0032 | B44: 45638 | C44: CUST041 | D44: Peter Richardson | E44: P001 | F44: Laptop | G44: Electronics | H44: 2 | I44: 899.99 | J44: Cash | K44: North | L44: Basic | M44: 44406 | N44: 1799.98 | P44: TRX0213 | Q44: 45745 | R44: CUST020 | S44: Margaret Wright | T44: P010 | U44: Keyboard | V44: Electronics | W44: 5 | X44: 89.99 | Y44: PayPal | Z44: South | AA44: Basic | AB44: 44704 | AC44: 449.95
A45: TRX0008 | B45: 45648 | C45: CUST007 | D45: David Martinez | E45: P008 | F45: Bookshelf | G45: Furniture | H45: 3 | I45: 149.99 | J45: Debit Card | K45: North | L45: Standard | M45: 44522 | N45: 449.97
A46: TRX0207 | B46: 45657 | C46: CUST025 | D46: Mark Carter | E46: P001 | F46: Laptop | G46: Electronics | H46: 1 | I46: 899.99 | J46: PayPal | K46: North | L46: Premium | M46: 45050 | N46: 899.99
A47: TRX0026 | B47: 45661 | C47: CUST037 | D47: Arthur Edwards | E47: P001 | F47: Laptop | G47: Electronics | H47: 1 | I47: 899.99 | J47: PayPal | K47: North | L47: Standard | M47: 44752 | N47: 899.99
A48: TRX0238 | B48: 45668 | C48: CUST038 | D48: Michelle Rogers | E48: P002 | F48: Smartphone | G48: Electronics | H48: 3 | I48: 699.99 | J48: Cash | K48: North | L48: Premium | M48: 44602 | N48: 2099.97
A49: TRX0022 | B49: 45670 | C49: CUST025 | D49: Mark Carter | E49: P007 | F49: Desk | G49: Furniture | H49: 1 | I49: 299.99 | J49: Credit Card | K49: North | L49: Basic | M49: 44436 | N49: 299.99
A50: TRX0087 | B50: 45671 | C50: CUST028 | D50: Betty Campbell | E50: P009 | F50: Monitor | G50: Electronics | H50: 4 | I50: 249.99 | J50: Credit Card | K50: North | L50: Premium | M50: 44460 | N50: 999.96
A51: TRX0107 | B51: 45671 | C51: CUST030 | D51: Helen Roberts | E51: P003 | F51: Headphones | G51: Electronics | H51: 2 | I51: 149.99 | J51: Cash | K51: North | L51: Standard | M51: 44913 | N51: 299.98
A52: TRX0024 | B52: 45695 | C52: CUST042 | D52: Ruth Brooks | E52: P008 | F52: Bookshelf | G52: Furniture | H52: 3 | I52: 149.99 | J52: Debit Card | K52: North | L52: Premium | M52: 44564 | N52: 449.97
A53: TRX0047 | B53: 45711 | C53: CUST042 | D53: Ruth Brooks | E53: P002 | F53: Smartphone | G53: Electronics | H53: 1 | I53: 699.99 | J53: Cash | K53: North | L53: Premium | M53: 44583 | N53: 699.99
A54: TRX0200 | B54: 45711 | C54: CUST037 | D54: Arthur Edwards | E54: P008 | F54: Bookshelf | G54: Furniture | H54: 4 | I54: 149.99 | J54: PayPal | K54: North | L54: Premium | M54: 44412 | N54: 599.96
A55: TRX0038 | B55: 45726 | C55: CUST035 | D55: Harry Morgan | E55: P009 | F55: Monitor | G55: Electronics | H55: 1 | I55: 249.99 | J55: Cash | K55: North | L55: Standard | M55: 45117 | N55: 249.99
A56: TRX0124 | B56: 45737 | C56: CUST040 | D56: Sharon Butler | E56: P001 | F56: Laptop | G56: Electronics | H56: 3 | I56: 899.99 | J56: Debit Card | K56: North | L56: Premium | M56: 44876 | N56: 2699.97
... A61: TRX0064 | B61: 45758 | C61: CUST031 | D61: Steven Turner | E61: P010 | F61: Keyboard | G61: Electronics | H61: 3 | I61: 89.99 | J61: Debit Card | K61: North | L61: Premium | M61: 44878 | N61: 269.97

Sheet FILTER ANALYSIS_E&W
A1: EAST REGION FILTER | P1: WEST REGION FILTER
A2: Transaction_ID | B2: Date | C2: Customer_ID | D2: Customer_Name | E2: Product_ID | F2: Product_Name | G2: Category | H2: Quantity | I2: Unit_Price | J2: Payment_Method | K2: Region | L2: Customer_Segment | M2: Customer_Since | N2: Total_Amount | P2: Transaction_ID | Q2: Date | R2: Customer_ID | S2: Customer_Name | T2: Product_ID | U2: Product_Name | V2: Category | W2: Quantity | X2: Unit_Price | Y2: Payment_Method | Z2: Region | AA2: Customer_Segment | AB2: Customer_Since | AC2: Total_Amount
A3: {=_xlfn._xlws.FILTER('Data Intelligence Dashboard'!A2:N251,'Data Intelligence Dashboard'!K2:K251="EAST")} -> TRX0135 | B3: 45405 | C3: CUST009 | D3: Robert Thomas | E3: P001 | F3: Laptop | G3: Electronics | H3: 3 | I3: 899.99 | J3: PayPal | K3: East | L3: Standard | M3: 45299 | N3: 2699.97 | P3: {=_xlfn._xlws.FILTER('Data Intelligence Dashboard'!A2:N251,'Data Intelligence Dashboard'!K2:K251="WEST")} -> TRX0092 | Q3: 45403 | R3: CUST024 | S3: Dorothy Nelson | T3: P005 | U3: Blender | V3: Appliances | W3: 2 | X3: 59.99 | Y3: Cash | Z3: West | AA3: Standard | AB3: 44746 | AC3: 119.98
A4: TRX0239 | B4: 45413 | C4: CUST012 | D4: Patricia Moore | E4: P002 | F4: Smartphone | G4: Electronics | H4: 4 | I4: 699.99 | J4: Cash | K4: East | L4: Standard | M4: 44409 | N4: 2799.96 | P4: TRX0185 | Q4: 45408 | R4: CUST026 | S4: Karen Hill | T4: P005 | U4: Blender | V4: Appliances | W4: 3 | X4: 59.99 | Y4: Cash | Z4: West | AA4: Premium | AB4: 45207 | AC4: 179.97
A5: TRX0040 | B5: 45424 | C5: CUST022 | D5: Susan Green | E5: P007 | F5: Desk | G5: Furniture | H5: 5 | I5: 299.99 | J5: PayPal | K5: East | L5: Basic | M5: 45168 | N5: 1499.95 | P5: TRX0138 | Q5: 45408 | R5: CUST022 | S5: Susan Green | T5: P008 | U5: Bookshelf | V5: Furniture | W5: 1 | X5: 149.99 | Y5: Credit Card | Z5: West | AA5: Standard | AB5: 45103 | AC5: 149.99
A6: TRX0235 | B6: 45424 | C6: CUST014 | D6: Linda Martin | E6: P004 | F6: Coffee Maker | G6: Appliances | H6: 3 | I6: 79.99 | J6: PayPal | K6: East | L6: Premium | M6: 45012 | N6: 239.97 | P6: TRX0191 | Q6: 45409 | R6: CUST038 | S6: Michelle Rogers | T6: P002 | U6: Smartphone | V6: Electronics | W6: 3 | X6: 699.99 | Y6: Credit Card | Z6: West | AA6: Basic | AB6: 44577 | AC6: 2099.97
A7: TRX0241 | B7: 45427 | C7: CUST029 | D7: Edward Mitchell | E7: P005 | F7: Blender | G7: Appliances | H7: 4 | I7: 59.99 | J7: Debit Card | K7: East | L7: Standard | M7: 44867 | N7: 239.96 | P7: TRX0122 | Q7: 45410 | R7: CUST025 | S7: Mark Carter | T7: P001 | U7: Laptop | V7: Electronics | W7: 4 | X7: 899.99 | Y7: Credit Card | Z7: West | AA7: Standard | AB7: 45327 | AC7: 3599.96
A8: TRX0232 | B8: 45434 | C8: CUST012 | D8: Patricia Moore | E8: P007 | F8: Desk | G8: Furniture | H8: 3 | I8: 299.99 | J8: Credit Card | K8: East | L8: Basic | M8: 44824 | N8: 899.97 | P8: TRX0231 | Q8: 45412 | R8: CUST018 | S8: Barbara Young | T8: P002 | U8: Smartphone | V8: Electronics | W8: 5 | X8: 699.99 | Y8: Cash | Z8: West | AA8: Basic | AB8: 45167 | AC8: 3499.95
A9: TRX0208 | B9: 45446 | C9: CUST004 | D9: Sarah Davis | E9: P010 | F9: Keyboard | G9: Electronics | H9: 5 | I9: 89.99 | J9: Credit Card | K9: East | L9: Standard | M9: 44587 | N9: 449.95 | P9: TRX0242 | Q9: 45416 | R9: CUST025 | S9: Mark Carter | T9: P007 | U9: Desk | V9: Furniture | W9: 4 | X9: 299.99 | Y9: Cash | Z9: West | AA9: Premium | AB9: 44716 | AC9: 1199.96
A10: TRX0234 | B10: 45449 | C10: CUST013 | D10: Joseph Jackson | E10: P009 | F10: Monitor | G10: Electronics | H10: 5 | I10: 249.99 | J10: Credit Card | K10: East | L10: Standard | M10: 44707 | N10: 1249.95 | P10: TRX0071 | Q10: 45422 | R10: CUST036 | S10: Nancy Collins | T10: P009 | U10: Monitor | V10: Electronics | W10: 5 | X10: 249.99 | Y10: Credit Card | Z10: West | AA10: Standard | AB10: 44525 | AC10: 1249.95
A11: TRX0220 | B11: 45450 | C11: CUST003 | D11: Michael Brown | E11: P008 | F11: Bookshelf | G11: Furniture | H11: 2 | I11: 149.99 | J11: Cash | K11: East | L11: Premium | M11: 44645 | N11: 299.98 | P11: TRX0194 | Q11: 45428 | R11: CUST006 | S11: Lisa Anderson | T11: P008 | U11: Bookshelf | V11: Furniture | W11: 2 | X11: 149.99 | Y11: Credit Card | Z11: West | AA11: Basic | AB11: 44823 | AC11: 299.98
A12: TRX0093 | B12: 45452 | C12: CUST050 | D12: Julie Foster | E12: P005 | F12: Blender | G12: Appliances | H12: 4 | I12: 59.99 | J12: Cash | K12: East | L12: Standard | M12: 44435 | N12: 239.96 | P12: TRX0130 | Q12: 45430 | R12: CUST002 | S12: Emma Wilson | T12: P008 | U12: Bookshelf | V12: Furniture | W12: 3 | X12: 149.99 | Y12: Credit Card | Z12: West | AA12: Premium | AB12: 45068 | AC12: 449.97
A13: TRX0044 | B13: 45459 | C13: CUST029 | D13: Edward Mitchell | E13: P001 | F13: Laptop | G13: Electronics | H13: 5 | I13: 899.99 | J13: PayPal | K13: East | L13: Premium | M13: 45278 | N13: 4499.95 | P13: TRX0041 | Q13: 45432 | R13: CUST021 | S13: Kevin Scott | T13: P001 | U13: Laptop | V13: Electronics | W13: 1 | X13: 899.99 | Y13: Credit Card | Z13: West | AA13: Premium | AB13: 44578 | AC13: 899.99
A14: TRX0150 | B14: 45460 | C14: CUST008 | D14: Jennifer Taylor | E14: P007 | F14: Desk | G14: Furniture | H14: 2 | I14: 299.99 | J14: Debit Card | K14: East | L14: Standard | M14: 45253 | N14: 599.98 | P14: TRX0015 | Q14: 45440 | R14: CUST008 | S14: Jennifer Taylor | T14: P002 | U14: Smartphone | V14: Electronics | W14: 5 | X14: 699.99 | Y14: PayPal | Z14: West | AA14: Standard | AB14: 44407 | AC14: 3499.95
A15: TRX0184 | B15: 45471 | C15: CUST046 | D15: Kathleen Bennett | E15: P002 | F15: Smartphone | G15: Electronics | H15: 3 | I15: 699.99 | J15: Credit Card | K15: East | L15: Premium | M15: 45102 | N15: 2099.97 | P15: TRX0128 | Q15: 45444 | R15: CUST040 | S15: Sharon Butler | T15: P005 | U15: Blender | V15: Appliances | W15: 2 | X15: 59.99 | Y15: Cash | Z15: West | AA15: Basic | AB15: 45390 | AC15: 119.98
... A49: TRX0116 | B49: 45756 | C49: CUST009 | D49: Robert Thomas | E49: P010 | F49: Keyboard | G49: Electronics | H49: 1 | I49: 89.99 | J49: Debit Card | K49: East | L49: Basic | M49: 45346 | N49: 89.99 | P49: TRX0250 | Q49: 45746 | R49: CUST026 | S49: Karen Hill | T49: P010 | U49: Keyboard | V49: Electronics | W49: 2 | X49: 89.99 | Y49: Debit Card | Z49: West | AA49: Premium | AB49: 44522 | AC49: 179.98
A50: TRX0103 | B50: 45758 | C50: CUST039 | D50: Lawrence Reed | E50: P010 | F50: Keyboard | G50: Electronics | H50: 2 | I50: 89.99 | J50: Debit Card | K50: East | L50: Basic | M50: 45088 | N50: 179.98

Sheet Scenario Summary
B2: Scenario Summary
D3: Current Values: | E3: Best Case | F3: Normal Case | G3: Worst Case
E4: Created by kalpesh patil on 9/22/2026 | F4: Created by kalpesh patil on 9/22/2026 | G4: Created by kalpesh patil on 9/22/2026
B5: Changing Cells:
C6: $H$2 | D6: 3 | E6: 5 | F6: 3 | G6: 1
C7: $I$2 | D7: 249.99 | E7: 249.99 | F7: 249.99 | G7: 59.99
B8: Result Cells:
C9: $U$3
B10: Notes: Current Values column represents values of changing cells at
B11: time Scenario Summary Report was created. Changing cells for each
B12: scenario are highlighted in gray.

Sheet REGRESSION ANALYSIS
A1: SUMMARY OUTPUT
A3: Regression Statistics
A4: Multiple R | B4: 0.45809869
A5: R Square | B5: 0.20985441
A6: Adjusted R Square | B6: 0.20665544
A7: Standard Error | B7: 921.40854
A8: Observations | B8: 249
A10: ANOVA
B11: df | C11: SS | D11: MS | E11: F | F11: Significance F
A12: Regression | B12: 1 | C12: 55694513 | D12: 55694513 | E12: 65.60062 | F12: 2.5391277e-14
A13: Residual | B13: 247 | C13: 2.0970144e+08 | D13: 848993.7
A14: Total | B14: 248 | C14: 2.6539596e+08
B16: Coefficients | C16: Standard Error | D16: t Stat | E16: P-value | F16: Lower 95% | G16: Upper 95% | H16: Lower 95.0% | I16: Upper 95.0%
A17: Intercept | B17: -148.18856 | C17: 143.94399 | D17: -1.0294877 | E17: 0.30425761 | F17: -431.70277 | G17: 135.32564 | H17: -431.70277 | I17: 135.32564
A18: 3 | B18: 353.7886 | C18: 43.680728 | D18: 8.0994209 | E18: 2.5391277e-14 | F18: 267.7544 | G18: 439.82281 | H18: 267.7544 | I18: 439.82281

Sheet HIGH VALUE CUSTOMERS
A1: CUSTOMER_ID | B1: CUSTOMER_NAME | C1: TOTAL_PURCHASE | E1: CUSTOMER_NAME | F1: CUSTOMER_ID | G1: PRODUCT_NAME | H1: CATEGORY | I1: TOTAL_PURCHASE | K1: TOP 3 CUSTOMERS
A2: {=_xlfn.UNIQUE('Data Intelligence Dashboard'!C2:C251)} -> CUST023 | B2: =_xlfn.XLOOKUP(A2,'Data Intelligence Dashboard'!C2:C251,'Data Intelligence Dashboard'!D2:D251) -> Paul Baker | C2: =SUMIF('Data Intelligence Dashboard'!C2:C251,A2,'Data Intelligence Dashboard'!N2:N251) -> 8559.77 | E2: {=_xlfn.TAKE(_xlfn.SORTBY(B2:B251,C2:C251,-1),10)} -> Mark Carter | F2: {=_xlfn.XLOOKUP(_xlfn.ANCHORARRAY(E2),$B$2:$B$251,$A$2:$A$251)} -> CUST025 | G2: {=_xlfn.XLOOKUP(_xlfn.ANCHORARRAY(E2),'Data Intelligence Dashboard'!$D$2:$D$251,'Data Intelligence Dashboard'!$F$2:$F$251)} -> Bookshelf | H2: {=_xlfn.XLOOKUP(_xlfn.ANCHORARRAY(E2),'Data Intelligence Dashboard'!$D$2:$D$251,'Data Intelligence Dashboard'!$G$2:$G$251)} -> Furniture | I2: {=_xlfn.XLOOKUP(_xlfn.ANCHORARRAY(E2),$B$2:$B$251,$C$2:$C$251)} -> 15659.65 | K2: CUSTOMER NAME | L2: TOTAL PURCHASE
A3: CUST013 | B3: =_xlfn.XLOOKUP(A3,'Data Intelligence Dashboard'!C3:C252,'Data Intelligence Dashboard'!D3:D252) -> Joseph Jackson | C3: =SUMIF('Data Intelligence Dashboard'!C3:C252,A3,'Data Intelligence Dashboard'!N3:N252) -> 6949.84 | E3: Edward Mitchell | F3: CUST029 | G3: Blender | H3: Appliances | I3: 11919.77 | K3: {=_xlfn.TAKE(_xlfn.SORTBY($B$2:$B$251,$C$2:$C$251,-1),3)} -> Mark Carter | L3: {=_xlfn.TAKE(_xlfn.SORTBY($C$2:$C$251,$C$2:$C$251,-1),3)} -> 15659.65
A4: CUST021 | B4: =_xlfn.XLOOKUP(A4,'Data Intelligence Dashboard'!C4:C253,'Data Intelligence Dashboard'!D4:D253) -> Kevin Scott | C4: =SUMIF('Data Intelligence Dashboard'!C4:C253,A4,'Data Intelligence Dashboard'!N4:N253) -> 3259.87 | E4: Barbara Young | F4: CUST018 | G4: Smartphone | H4: Electronics | I4: 10649.8 | K4: Edward Mitchell | L4: 11919.77
A5: CUST046 | B5: =_xlfn.XLOOKUP(A5,'Data Intelligence Dashboard'!C5:C254,'Data Intelligence Dashboard'!D5:D254) -> Kathleen Bennett | C5: =SUMIF('Data Intelligence Dashboard'!C5:C254,A5,'Data Intelligence Dashboard'!N5:N254) -> 4309.81 | E5: Patricia Moore | F5: CUST012 | G5: Smartphone | H5: Electronics | I5: 9799.73 | K5: Barbara Young | L5: 10649.8
A6: CUST003 | B6: =_xlfn.XLOOKUP(A6,'Data Intelligence Dashboard'!C6:C255,'Data Intelligence Dashboard'!D6:D255) -> Michael Brown | C6: =SUMIF('Data Intelligence Dashboard'!C6:C255,A6,'Data Intelligence Dashboard'!N6:N255) -> 6169.74 | E6: Paul Baker | F6: CUST023 | G6: Monitor | H6: Electronics | I6: 8559.77
A7: CUST024 | B7: =_xlfn.XLOOKUP(A7,'Data Intelligence Dashboard'!C7:C256,'Data Intelligence Dashboard'!D7:D256) -> Dorothy Nelson | C7: =SUMIF('Data Intelligence Dashboard'!C7:C256,A7,'Data Intelligence Dashboard'!N7:N256) -> 8269.79 | E7: Dorothy Nelson | F7: CUST024 | G7: Blender | H7: Appliances | I7: 8269.79
A8: CUST017 | B8: =_xlfn.XLOOKUP(A8,'Data Intelligence Dashboard'!C8:C257,'Data Intelligence Dashboard'!D8:D257) -> Charles Allen | C8: =SUMIF('Data Intelligence Dashboard'!C8:C257,A8,'Data Intelligence Dashboard'!N8:N257) -> 5089.73 | E8: Karen Hill | F8: CUST026 | G8: Blender | H8: Appliances | I8: 8009.77
A9: CUST009 | B9: =_xlfn.XLOOKUP(A9,'Data Intelligence Dashboard'!C9:C258,'Data Intelligence Dashboard'!D9:D258) -> Robert Thomas | C9: =SUMIF('Data Intelligence Dashboard'!C9:C258,A9,'Data Intelligence Dashboard'!N9:N258) -> 3509.9 | E9: Daniel King | F9: CUST019 | G9: Coffee Maker | H9: Appliances | I9: 7309.8
A10: CUST026 | B10: =_xlfn.XLOOKUP(A10,'Data Intelligence Dashboard'!C10:C259,'Data Intelligence Dashboard'!D10:D259) -> Karen Hill | C10: =SUMIF('Data Intelligence Dashboard'!C10:C259,A10,'Data Intelligence Dashboard'!N10:N259) -> 8009.77 | E10: Lawrence Reed | F10: CUST039 | G10: Coffee Maker | H10: Appliances | I10: 6989.77
A11: CUST022 | B11: =_xlfn.XLOOKUP(A11,'Data Intelligence Dashboard'!C11:C260,'Data Intelligence Dashboard'!D11:D260) -> Susan Green | C11: =SUMIF('Data Intelligence Dashboard'!C11:C260,A11,'Data Intelligence Dashboard'!N11:N260) -> 1979.89 | E11: Joseph Jackson | F11: CUST013 | G11: Monitor | H11: Electronics | I11: 6949.84
A12: CUST041 | B12: =_xlfn.XLOOKUP(A12,'Data Intelligence Dashboard'!C12:C261,'Data Intelligence Dashboard'!D12:D261) -> Peter Richardson | C12: =SUMIF('Data Intelligence Dashboard'!C12:C261,A12,'Data Intelligence Dashboard'!N12:N261) -> 5949.85 | E12: TOP 10 HIGH VALUE CUSTOMERS
A13: CUST043 | B13: =_xlfn.XLOOKUP(A13,'Data Intelligence Dashboard'!C13:C262,'Data Intelligence Dashboard'!D13:D262) -> Dennis Gray | C13: =SUMIF('Data Intelligence Dashboard'!C13:C262,A13,'Data Intelligence Dashboard'!N13:N262) -> 479.92
A14: CUST038 | B14: =_xlfn.XLOOKUP(A14,'Data Intelligence Dashboard'!C14:C263,'Data Intelligence Dashboard'!D14:D263) -> Michelle Rogers | C14: =SUMIF('Data Intelligence Dashboard'!C14:C263,A14,'Data Intelligence Dashboard'!N14:N263) -> 4199.94
A15: CUST027 | B15: =_xlfn.XLOOKUP(A15,'Data Intelligence Dashboard'!C15:C264,'Data Intelligence Dashboard'!D15:D264) -> George Adams | C15: =SUMIF('Data Intelligence Dashboard'!C15:C264,A15,'Data Intelligence Dashboard'!N15:N264) -> 3779.93
A16: CUST025 | B16: =_xlfn.XLOOKUP(A16,'Data Intelligence Dashboard'!C16:C265,'Data Intelligence Dashboard'!D16:D265) -> Mark Carter | C16: =SUMIF('Data Intelligence Dashboard'!C16:C265,A16,'Data Intelligence Dashboard'!N16:N265) -> 15659.65
A17: CUST010 | B17: =_xlfn.XLOOKUP(A17,'Data Intelligence Dashboard'!C17:C266,'Data Intelligence Dashboard'!D17:D266) -> Maria Garcia | C17: =SUMIF('Data Intelligence Dashboard'!C17:C266,A17,'Data Intelligence Dashboard'!N17:N266) -> 1909.93
A18: CUST048 | B18: =_xlfn.XLOOKUP(A18,'Data Intelligence Dashboard'!C18:C267,'Data Intelligence Dashboard'!D18:D267) -> Virginia Sanders | C18: =SUMIF('Data Intelligence Dashboard'!C18:C267,A18,'Data Intelligence Dashboard'!N18:N267) -> 4789.79
A19: CUST018 | B19: =_xlfn.XLOOKUP(A19,'Data Intelligence Dashboard'!C19:C268,'Data Intelligence Dashboard'!D19:D268) -> Barbara Young | C19: =SUMIF('Data Intelligence Dashboard'!C19:C268,A19,'Data Intelligence Dashboard'!N19:N268) -> 10649.8
A20: CUST012 | B20: =_xlfn.XLOOKUP(A20,'Data Intelligence Dashboard'!C20:C269,'Data Intelligence Dashboard'!D20:D269) -> Patricia Moore | C20: =SUMIF('Data Intelligence Dashboard'!C20:C269,A20,'Data Intelligence Dashboard'!N20:N269) -> 9799.73
A21: CUST044 | B21: =_xlfn.XLOOKUP(A21,'Data Intelligence Dashboard'!C21:C270,'Data Intelligence Dashboard'!D21:D270) -> Cynthia Price | C21: =SUMIF('Data Intelligence Dashboard'!C21:C270,A21,'Data Intelligence Dashboard'!N21:N270) -> 3769.83
A22: CUST036 | B22: =_xlfn.XLOOKUP(A22,'Data Intelligence Dashboard'!C22:C271,'Data Intelligence Dashboard'!D22:D271) -> Nancy Collins | C22: =SUMIF('Data Intelligence Dashboard'!C22:C271,A22,'Data Intelligence Dashboard'!N22:N271) -> 4189.77
A23: CUST014 | B23: =_xlfn.XLOOKUP(A23,'Data Intelligence Dashboard'!C23:C272,'Data Intelligence Dashboard'!D23:D272) -> Linda Martin | C23: =SUMIF('Data Intelligence Dashboard'!C23:C272,A23,'Data Intelligence Dashboard'!N23:N272) -> 1289.9
A24: CUST030 | B24: =_xlfn.XLOOKUP(A24,'Data Intelligence Dashboard'!C24:C273,'Data Intelligence Dashboard'!D24:D273) -> Helen Roberts | C24: =SUMIF('Data Intelligence Dashboard'!C24:C273,A24,'Data Intelligence Dashboard'!N24:N273) -> 6459.79
... A51: CUST001 | B51: =_xlfn.XLOOKUP(A51,'Data Intelligence Dashboard'!C51:C300,'Data Intelligence Dashboard'!D51:D300) -> John Smith | C51: =SUMIF('Data Intelligence Dashboard'!C51:C300,A51,'Data Intelligence Dashboard'!N51:N300) -> 599.96

Sheet FREQUENCY ANALYSIS
A1: PRODUCT_NAME | B1: PURCHASE_COUNT | E1: LIST COMPARISON – MATCHING NAMES | K1: CUSTOMER ABBREVIATIONS
A2: {=_xlfn.UNIQUE('Data Intelligence Dashboard'!F2:F251)} -> Monitor | B2: {=COUNTIF('Data Intelligence Dashboard'!F2:F251,_xlfn.ANCHORARRAY(A2))} -> 26
A3: Blender | B3: 29 | E3: LIST_1 | F3: LIST_2 | G3: MATCHING_NAMES | K3: CUSTOMER_NAME | L3: ABBREVIATION
A4: Bookshelf | B4: 35 | E4: ='Data Intelligence Dashboard'!D2 -> Paul Baker | F4: {=_xlfn._xlws.FILTER('HIGH VALUE CUSTOMERS'!E2:E11,'HIGH VALUE CUSTOMERS'!E2:E11<>"")} -> Mark Carter | G4: {=_xlfn.UNIQUE(_xlfn._xlws.FILTER(E4:E253,COUNTIF(F4:F13,E4:E253)>0))} -> Paul Baker | K4: =E4 -> Paul Baker | L4: =LEFT(K4,1)&LEFT(RIGHT(K4,LEN(K4)-FIND(" ",K4)),1) -> PB
A5: Headphones | B5: 16 | E5: ='Data Intelligence Dashboard'!D3 -> Joseph Jackson | F5: Edward Mitchell | G5: Joseph Jackson | K5: =E5 -> Joseph Jackson | L5: =LEFT(K5,1)&LEFT(RIGHT(K5,LEN(K5)-FIND(" ",K5)),1) -> JJ
A6: Laptop | B6: 24 | E6: ='Data Intelligence Dashboard'!D4 -> Kevin Scott | F6: Barbara Young | G6: Dorothy Nelson | K6: =E6 -> Kevin Scott | L6: =LEFT(K6,1)&LEFT(RIGHT(K6,LEN(K6)-FIND(" ",K6)),1) -> KS
A7: Smartphone | B7: 31 | E7: ='Data Intelligence Dashboard'!D5 -> Kathleen Bennett | F7: Patricia Moore | G7: Karen Hill | K7: =E7 -> Kathleen Bennett | L7: =LEFT(K7,1)&LEFT(RIGHT(K7,LEN(K7)-FIND(" ",K7)),1) -> KB
A8: Desk | B8: 26 | E8: ='Data Intelligence Dashboard'!D6 -> Michael Brown | F8: Paul Baker | G8: Mark Carter | K8: =E8 -> Michael Brown | L8: =LEFT(K8,1)&LEFT(RIGHT(K8,LEN(K8)-FIND(" ",K8)),1) -> MB
A9: Coffee Maker | B9: 14 | E9: ='Data Intelligence Dashboard'!D7 -> Dorothy Nelson | F9: Dorothy Nelson | G9: Barbara Young | K9: =E9 -> Dorothy Nelson | L9: =LEFT(K9,1)&LEFT(RIGHT(K9,LEN(K9)-FIND(" ",K9)),1) -> DN
A10: Keyboard | B10: 34 | E10: ='Data Intelligence Dashboard'!D8 -> Dorothy Nelson | F10: Karen Hill | G10: Patricia Moore | K10: =E10 -> Dorothy Nelson | L10: =LEFT(K10,1)&LEFT(RIGHT(K10,LEN(K10)-FIND(" ",K10)),1) -> DN
A11: Office Chair | B11: 15 | E11: ='Data Intelligence Dashboard'!D9 -> Charles Allen | F11: Daniel King | G11: Edward Mitchell | K11: =E11 -> Charles Allen | L11: =LEFT(K11,1)&LEFT(RIGHT(K11,LEN(K11)-FIND(" ",K11)),1) -> CA
E12: ='Data Intelligence Dashboard'!D10 -> Robert Thomas | F12: Lawrence Reed | G12: Daniel King | K12: =E12 -> Robert Thomas | L12: =LEFT(K12,1)&LEFT(RIGHT(K12,LEN(K12)-FIND(" ",K12)),1) -> RT
E13: ='Data Intelligence Dashboard'!D11 -> Karen Hill | F13: Joseph Jackson | G13: Lawrence Reed | K13: =E13 -> Karen Hill | L13: =LEFT(K13,1)&LEFT(RIGHT(K13,LEN(K13)-FIND(" ",K13)),1) -> KH
A14: MOST_FREQUENT_PRODUCT | E14: ='Data Intelligence Dashboard'!D12 -> Susan Green | K14: =E14 -> Susan Green | L14: =LEFT(K14,1)&LEFT(RIGHT(K14,LEN(K14)-FIND(" ",K14)),1) -> SG
A15: =INDEX(A2:A10,MATCH(MAX(B2:B10),B2:B10,0)) -> Bookshelf | E15: ='Data Intelligence Dashboard'!D13 -> Kathleen Bennett | K15: =E15 -> Kathleen Bennett | L15: =LEFT(K15,1)&LEFT(RIGHT(K15,LEN(K15)-FIND(" ",K15)),1) -> KB
E16: ='Data Intelligence Dashboard'!D14 -> Peter Richardson | K16: =E16 -> Peter Richardson | L16: =LEFT(K16,1)&LEFT(RIGHT(K16,LEN(K16)-FIND(" ",K16)),1) -> PR
E17: ='Data Intelligence Dashboard'!D15 -> Dennis Gray | K17: =E17 -> Dennis Gray | L17: =LEFT(K17,1)&LEFT(RIGHT(K17,LEN(K17)-FIND(" ",K17)),1) -> DG
E18: ='Data Intelligence Dashboard'!D16 -> Michelle Rogers | K18: =E18 -> Michelle Rogers | L18: =LEFT(K18,1)&LEFT(RIGHT(K18,LEN(K18)-FIND(" ",K18)),1) -> MR
E19: ='Data Intelligence Dashboard'!D17 -> George Adams | K19: =E19 -> George Adams | L19: =LEFT(K19,1)&LEFT(RIGHT(K19,LEN(K19)-FIND(" ",K19)),1) -> GA
E20: ='Data Intelligence Dashboard'!D18 -> Mark Carter | K20: =E20 -> Mark Carter | L20: =LEFT(K20,1)&LEFT(RIGHT(K20,LEN(K20)-FIND(" ",K20)),1) -> MC
E21: ='Data Intelligence Dashboard'!D19 -> Maria Garcia | K21: =E21 -> Maria Garcia | L21: =LEFT(K21,1)&LEFT(RIGHT(K21,LEN(K21)-FIND(" ",K21)),1) -> MG
E22: ='Data Intelligence Dashboard'!D20 -> Mark Carter | K22: =E22 -> Mark Carter | L22: =LEFT(K22,1)&LEFT(RIGHT(K22,LEN(K22)-FIND(" ",K22)),1) -> MC
E23: ='Data Intelligence Dashboard'!D21 -> Virginia Sanders | K23: =E23 -> Virginia Sanders | L23: =LEFT(K23,1)&LEFT(RIGHT(K23,LEN(K23)-FIND(" ",K23)),1) -> VS
E24: ='Data Intelligence Dashboard'!D22 -> Barbara Young | K24: =E24 -> Barbara Young | L24: =LEFT(K24,1)&LEFT(RIGHT(K24,LEN(K24)-FIND(" ",K24)),1) -> BY
E25: ='Data Intelligence Dashboard'!D23 -> Patricia Moore | K25: =E25 -> Patricia Moore | L25: =LEFT(K25,1)&LEFT(RIGHT(K25,LEN(K25)-FIND(" ",K25)),1) -> PM
E26: ='Data Intelligence Dashboard'!D24 -> Cynthia Price | K26: =E26 -> Cynthia Price | L26: =LEFT(K26,1)&LEFT(RIGHT(K26,LEN(K26)-FIND(" ",K26)),1) -> CP
E27: ='Data Intelligence Dashboard'!D25 -> Mark Carter | K27: =E27 -> Mark Carter | L27: =LEFT(K27,1)&LEFT(RIGHT(K27,LEN(K27)-FIND(" ",K27)),1) -> MC
... E253: ='Data Intelligence Dashboard'!D251 -> Steven Turner | K253: =E253 -> Steven Turner | L253: =LEFT(K253,1)&LEFT(RIGHT(K253,LEN(K253)-FIND(" ",K253)),1) -> ST
